mse/__init__.py
mse/methods.py
mse-0.1.4.dist-info/LICENSE
mse-0.1.4.dist-info/METADATA
mse-0.1.4.dist-info/WHEEL
mse-0.1.4.dist-info/top_level.txt
mse-0.1.4.dist-info/RECORD
