Metadata-Version: 2.1
Name: mse
Version: 0.1.4
Summary: Make Structs Easy (MSE)
Home-page: https://github.com/fqaiser94/mse
Author: fqaiser94
Author-email: 
License: Apache license 2.0
Keywords: pyspark,struct,StructType,add,drop,rename
Platform: UNKNOWN
Classifier: Development Status :: 4 - Beta
Classifier: Intended Audience :: Developers
Classifier: Topic :: Software Development :: Build Tools
Classifier: License :: OSI Approved :: Apache Software License
Classifier: Programming Language :: Python :: 3
Classifier: Programming Language :: Python :: 3.4
Classifier: Programming Language :: Python :: 3.5
Classifier: Programming Language :: Python :: 3.6
Classifier: Programming Language :: Python :: 3.7
Requires-Dist: pyspark (>=2.4)
